CHANGELOG.txt
LICENSE.txt
MANIFEST.in
README.txt
ez_setup.py
setup.cfg
setup.py
PermissionKit.egg-info/PKG-INFO
PermissionKit.egg-info/SOURCES.txt
PermissionKit.egg-info/dependency_links.txt
PermissionKit.egg-info/entry_points.txt
PermissionKit.egg-info/not-zip-safe
PermissionKit.egg-info/requires.txt
PermissionKit.egg-info/top_level.txt
doc/Makefile
doc/index.txt
doc/source/api.rst
doc/source/conf.py
doc/source/index.rst
doc/source/manual.rst
example/README.txt
permissionkit/__init__.py
permissionkit/check.py
permissionkit/fail.py
permissionkit/user.py
test/README.txt
test/doc.py