Metadata-Version: 1.0
Name: PermissionKit
Version: 0.5.2
Summary: A very simple framework for creating permission objects and using them in authorization checks.
Home-page: UNKNOWN
Author: James Gardner
Author-email: UNKNOWN
License: GPLv3
Platform: UNKNOWN
Classifier: Development Status :: 3 - Alpha
Classifier: License :: OSI Approved :: GNU Affero General Public License v3
Classifier: Programming Language :: Python
